[
  {
    "name": "Lion",
    "attrs": [
      "cont_afrique",
      "milieu_savane",
      "classe_mammifere",
      "regime_carnivore",
      "taille_100k+",
      "syl_on",
      "lettre_l",
      "carac_groupe"
    ]
  },
  {
    "name": "Éléphant",
    "attrs": [
      "cont_afrique",
      "cont_asie",
      "milieu_savane",
      "milieu_foret",
      "classe_mammifere",
      "regime_herbivore",
      "taille_1000k+",
      "lettre_e",
      "carac_menace"
    ]
  },
  {
    "name": "Girafe",
    "attrs": [
      "cont_afrique",
      "milieu_savane",
      "classe_mammifere",
      "regime_herbivore",
      "taille_1000k+",
      "lettre_g",
      "carac_menace"
    ]
  },
  {
    "name": "Zèbre",
    "attrs": [
      "cont_afrique",
      "milieu_savane",
      "classe_mammifere",
      "regime_herbivore",
      "taille_100k+",
      "lettre_z",
      "carac_groupe"
    ]
  },
  {
    "name": "Hippopotame",
    "attrs": [
      "cont_afrique",
      "milieu_eau",
      "milieu_savane",
      "classe_mammifere",
      "regime_herbivore",
      "taille_1000k+",
      "lettre_h",
      "carac_menace"
    ]
  },
  {
    "name": "Crocodile",
    "attrs": [
      "cont_afrique",
      "cont_asie",
      "cont_amerique",
      "milieu_eau",
      "milieu_savane",
      "classe_reptile",
      "regime_carnivore",
      "taille_100k+",
      "syl_ile",
      "lettre_c",
      "carac_ovipare"
    ]
  },
  {
    "name": "Gorille",
    "attrs": [
      "cont_afrique",
      "milieu_foret",
      "classe_mammifere",
      "regime_herbivore",
      "taille_100k+",
      "syl_ille",
      "lettre_g",
      "carac_menace",
      "carac_groupe"
    ]
  },
  {
    "name": "Chimpanzé",
    "attrs": [
      "cont_afrique",
      "milieu_foret",
      "classe_mammifere",
      "regime_omnivore",
      "taille_100k+",
      "lettre_c",
      "carac_menace",
      "carac_groupe"
    ]
  },
  {
    "name": "Rhinocéros",
    "attrs": [
      "cont_afrique",
      "cont_asie",
      "milieu_savane",
      "classe_mammifere",
      "regime_herbivore",
      "taille_1000k+",
      "lettre_r",
      "carac_menace"
    ]
  },
  {
    "name": "Guépard",
    "attrs": [
      "cont_afrique",
      "milieu_savane",
      "classe_mammifere",
      "regime_carnivore",
      "taille_100k+",
      "lettre_g",
      "carac_menace"
    ]
  },
  {
    "name": "Léopard",
    "attrs": [
      "cont_afrique",
      "cont_asie",
      "milieu_foret",
      "milieu_savane",
      "classe_mammifere",
      "regime_carnivore",
      "taille_100k+",
      "lettre_l",
      "carac_menace",
      "carac_nocturne"
    ]
  },
  {
    "name": "Hyène",
    "attrs": [
      "cont_afrique",
      "milieu_savane",
      "classe_mammifere",
      "regime_carnivore",
      "taille_100k+",
      "lettre_h",
      "carac_nocturne",
      "carac_groupe"
    ]
  },
  {
    "name": "Flamant rose",
    "attrs": [
      "cont_afrique",
      "cont_europe",
      "milieu_eau",
      "classe_oiseau",
      "regime_omnivore",
      "taille_10k+",
      "lettre_f",
      "carac_migrateur",
      "carac_ovipare",
      "carac_groupe"
    ]
  },
  {
    "name": "Autruche",
    "attrs": [
      "cont_afrique",
      "milieu_savane",
      "classe_oiseau",
      "regime_omnivore",
      "taille_100k+",
      "lettre_a",
      "carac_ovipare"
    ]
  },
  {
    "name": "Mamba noir",
    "attrs": [
      "cont_afrique",
      "milieu_savane",
      "classe_reptile",
      "regime_carnivore",
      "taille_10k+",
      "lettre_m",
      "carac_venimeux",
      "carac_ovipare"
    ]
  },
  {
    "name": "Mandrill",
    "attrs": [
      "cont_afrique",
      "milieu_foret",
      "classe_mammifere",
      "regime_omnivore",
      "taille_10k+",
      "lettre_m",
      "carac_groupe"
    ]
  },
  {
    "name": "Okapi",
    "attrs": [
      "cont_afrique",
      "milieu_foret",
      "classe_mammifere",
      "regime_herbivore",
      "taille_100k+",
      "lettre_o",
      "carac_menace"
    ]
  },
  {
    "name": "Serval",
    "attrs": [
      "cont_afrique",
      "milieu_savane",
      "classe_mammifere",
      "regime_carnivore",
      "taille_10k+",
      "lettre_s",
      "carac_nocturne"
    ]
  },
  {
    "name": "Lycaon",
    "attrs": [
      "cont_afrique",
      "milieu_savane",
      "classe_mammifere",
      "regime_carnivore",
      "taille_10k+",
      "syl_on",
      "lettre_l",
      "carac_menace",
      "carac_groupe"
    ]
  },
  {
    "name": "Pangolin",
    "attrs": [
      "cont_afrique",
      "cont_asie",
      "milieu_foret",
      "classe_mammifere",
      "regime_carnivore",
      "taille_10k+",
      "lettre_p",
      "carac_menace",
      "carac_nocturne"
    ]
  },
  {
    "name": "Tigre",
    "attrs": [
      "cont_asie",
      "milieu_foret",
      "classe_mammifere",
      "regime_carnivore",
      "taille_100k+",
      "lettre_t",
      "carac_menace",
      "carac_solitaire",
      "carac_nageur"
    ]
  },
  {
    "name": "Panda géant",
    "attrs": [
      "cont_asie",
      "milieu_foret",
      "classe_mammifere",
      "regime_herbivore",
      "taille_100k+",
      "lettre_p",
      "carac_menace"
    ]
  },
  {
    "name": "Orang-outan",
    "attrs": [
      "cont_asie",
      "milieu_foret",
      "classe_mammifere",
      "regime_omnivore",
      "taille_100k+",
      "lettre_o",
      "carac_menace",
      "carac_arboricole"
    ]
  },
  {
    "name": "Komodo",
    "attrs": [
      "cont_asie",
      "milieu_savane",
      "classe_reptile",
      "regime_carnivore",
      "taille_100k+",
      "lettre_c",
      "carac_venimeux",
      "carac_ovipare"
    ]
  },
  {
    "name": "Cobra royal",
    "attrs": [
      "cont_asie",
      "milieu_foret",
      "classe_reptile",
      "regime_carnivore",
      "taille_10k+",
      "lettre_c",
      "carac_venimeux",
      "carac_ovipare"
    ]
  },
  {
    "name": "Éléphant d'Asie",
    "attrs": [
      "cont_asie",
      "milieu_foret",
      "classe_mammifere",
      "regime_herbivore",
      "taille_1000k+",
      "lettre_e",
      "carac_menace",
      "carac_groupe"
    ]
  },
  {
    "name": "Macaque",
    "attrs": [
      "cont_asie",
      "milieu_foret",
      "classe_mammifere",
      "regime_omnivore",
      "taille_10k+",
      "lettre_m",
      "carac_groupe"
    ]
  },
  {
    "name": "Tapir",
    "attrs": [
      "cont_asie",
      "cont_amerique",
      "milieu_foret",
      "classe_mammifere",
      "regime_herbivore",
      "taille_100k+",
      "lettre_t",
      "carac_menace",
      "carac_nageur"
    ]
  },
  {
    "name": "Gibbon",
    "attrs": [
      "cont_asie",
      "milieu_foret",
      "classe_mammifere",
      "regime_omnivore",
      "taille_10k+",
      "syl_on",
      "lettre_g",
      "carac_menace",
      "carac_arboricole"
    ]
  },
  {
    "name": "Python",
    "attrs": [
      "cont_asie",
      "cont_afrique",
      "milieu_foret",
      "classe_reptile",
      "regime_carnivore",
      "taille_10k+",
      "syl_on",
      "lettre_p",
      "carac_ovipare"
    ]
  },
  {
    "name": "Paon",
    "attrs": [
      "cont_asie",
      "milieu_foret",
      "classe_oiseau",
      "regime_omnivore",
      "taille_10k+",
      "syl_on",
      "lettre_p",
      "carac_ovipare"
    ]
  },
  {
    "name": "Yak",
    "attrs": [
      "cont_asie",
      "milieu_montagne",
      "classe_mammifere",
      "regime_herbivore",
      "taille_100k+",
      "lettre_y",
      "carac_groupe"
    ]
  },
  {
    "name": "Ours polaire",
    "attrs": [
      "cont_arctique",
      "milieu_mer",
      "milieu_montagne",
      "classe_mammifere",
      "regime_carnivore",
      "taille_100k+",
      "lettre_o",
      "carac_menace",
      "carac_nageur",
      "carac_solitaire"
    ]
  },
  {
    "name": "Morse",
    "attrs": [
      "cont_arctique",
      "milieu_mer",
      "classe_mammifere",
      "regime_carnivore",
      "taille_100k+",
      "lettre_m",
      "carac_groupe"
    ]
  },
  {
    "name": "Renard arctique",
    "attrs": [
      "cont_arctique",
      "milieu_montagne",
      "classe_mammifere",
      "regime_omnivore",
      "taille_10k+",
      "lettre_r",
      "carac_menace"
    ]
  },
  {
    "name": "Béluga",
    "attrs": [
      "cont_arctique",
      "milieu_mer",
      "classe_mammifere",
      "regime_carnivore",
      "taille_1000k+",
      "lettre_b",
      "carac_menace",
      "carac_groupe"
    ]
  },
  {
    "name": "Narval",
    "attrs": [
      "cont_arctique",
      "milieu_mer",
      "classe_mammifere",
      "regime_carnivore",
      "taille_1000k+",
      "lettre_n",
      "carac_menace",
      "carac_groupe"
    ]
  },
  {
    "name": "Jaguar",
    "attrs": [
      "cont_amerique",
      "milieu_foret",
      "classe_mammifere",
      "regime_carnivore",
      "taille_100k+",
      "lettre_j",
      "carac_menace",
      "carac_nageur",
      "carac_solitaire"
    ]
  },
  {
    "name": "Anaconda",
    "attrs": [
      "cont_amerique",
      "milieu_eau",
      "milieu_foret",
      "classe_reptile",
      "regime_carnivore",
      "taille_100k+",
      "lettre_a",
      "carac_nageur"
    ]
  },
  {
    "name": "Toucan",
    "attrs": [
      "cont_amerique",
      "milieu_foret",
      "classe_oiseau",
      "regime_omnivore",
      "taille_1k+",
      "syl_an",
      "lettre_t",
      "carac_ovipare",
      "carac_arboricole"
    ]
  },
  {
    "name": "Lama",
    "attrs": [
      "cont_amerique",
      "milieu_montagne",
      "classe_mammifere",
      "regime_herbivore",
      "taille_100k+",
      "lettre_l",
      "carac_groupe"
    ]
  },
  {
    "name": "Condor",
    "attrs": [
      "cont_amerique",
      "milieu_montagne",
      "classe_oiseau",
      "regime_carnivore",
      "taille_10k+",
      "syl_on",
      "lettre_c",
      "carac_ovipare",
      "carac_menace"
    ]
  },
  {
    "name": "Tatou",
    "attrs": [
      "cont_amerique",
      "milieu_foret",
      "milieu_savane",
      "classe_mammifere",
      "regime_omnivore",
      "taille_10k+",
      "lettre_t",
      "carac_nocturne",
      "carac_ovipare"
    ]
  },
  {
    "name": "Piranha",
    "attrs": [
      "cont_amerique",
      "milieu_eau",
      "classe_poisson",
      "regime_carnivore",
      "taille_1k+",
      "lettre_p",
      "carac_groupe"
    ]
  },
  {
    "name": "Caïman",
    "attrs": [
      "cont_amerique",
      "milieu_eau",
      "milieu_foret",
      "classe_reptile",
      "regime_carnivore",
      "taille_100k+",
      "syl_an",
      "lettre_c",
      "carac_ovipare"
    ]
  },
  {
    "name": "Alpaga",
    "attrs": [
      "cont_amerique",
      "milieu_montagne",
      "classe_mammifere",
      "regime_herbivore",
      "taille_100k+",
      "lettre_a",
      "carac_groupe",
      "carac_domestique"
    ]
  },
  {
    "name": "Fourmilier",
    "attrs": [
      "cont_amerique",
      "milieu_foret",
      "milieu_savane",
      "classe_mammifere",
      "regime_carnivore",
      "taille_10k+",
      "lettre_f",
      "carac_solitaire"
    ]
  },
  {
    "name": "Paresseux",
    "attrs": [
      "cont_amerique",
      "milieu_foret",
      "classe_mammifere",
      "regime_herbivore",
      "taille_10k+",
      "lettre_p",
      "carac_arboricole",
      "carac_solitaire",
      "carac_menace"
    ]
  },
  {
    "name": "Manchot",
    "attrs": [
      "cont_antarctique",
      "milieu_mer",
      "classe_oiseau",
      "regime_carnivore",
      "taille_10k+",
      "syl_ot",
      "lettre_m",
      "carac_ovipare",
      "carac_groupe",
      "carac_nageur"
    ]
  },
  {
    "name": "Léopard de mer",
    "attrs": [
      "cont_antarctique",
      "milieu_mer",
      "classe_mammifere",
      "regime_carnivore",
      "taille_100k+",
      "lettre_l",
      "carac_solitaire",
      "carac_nageur"
    ]
  },
  {
    "name": "Albatros",
    "attrs": [
      "cont_antarctique",
      "milieu_mer",
      "classe_oiseau",
      "regime_carnivore",
      "taille_10k+",
      "lettre_a",
      "carac_ovipare",
      "carac_migrateur"
    ]
  },
  {
    "name": "Orque",
    "attrs": [
      "cont_antarctique",
      "cont_arctique",
      "milieu_mer",
      "classe_mammifere",
      "regime_carnivore",
      "taille_1000k+",
      "lettre_o",
      "carac_groupe",
      "carac_nageur"
    ]
  },
  {
    "name": "Kangourou",
    "attrs": [
      "cont_oceanie",
      "milieu_savane",
      "classe_mammifere",
      "regime_herbivore",
      "taille_100k+",
      "lettre_k",
      "carac_groupe"
    ]
  },
  {
    "name": "Koala",
    "attrs": [
      "cont_oceanie",
      "milieu_foret",
      "classe_mammifere",
      "regime_herbivore",
      "taille_10k+",
      "lettre_k",
      "carac_arboricole",
      "carac_menace"
    ]
  },
  {
    "name": "Wallaby",
    "attrs": [
      "cont_oceanie",
      "milieu_savane",
      "classe_mammifere",
      "regime_herbivore",
      "taille_10k+",
      "lettre_v",
      "carac_groupe"
    ]
  },
  {
    "name": "Wombat",
    "attrs": [
      "cont_oceanie",
      "milieu_foret",
      "classe_mammifere",
      "regime_herbivore",
      "taille_10k+",
      "lettre_v",
      "carac_nocturne",
      "carac_solitaire"
    ]
  },
  {
    "name": "Ornithorynque",
    "attrs": [
      "cont_oceanie",
      "milieu_eau",
      "classe_mammifere",
      "regime_carnivore",
      "taille_1k+",
      "lettre_o",
      "carac_venimeux",
      "carac_ovipare",
      "carac_nageur"
    ]
  },
  {
    "name": "Diable de Tasmanie",
    "attrs": [
      "cont_oceanie",
      "milieu_foret",
      "classe_mammifere",
      "regime_carnivore",
      "taille_10k+",
      "lettre_d",
      "carac_menace",
      "carac_nocturne"
    ]
  },
  {
    "name": "Cacatoès",
    "attrs": [
      "cont_oceanie",
      "milieu_foret",
      "classe_oiseau",
      "regime_herbivore",
      "taille_1k+",
      "lettre_c",
      "carac_ovipare",
      "carac_arboricole",
      "carac_groupe"
    ]
  },
  {
    "name": "Loup",
    "attrs": [
      "cont_europe",
      "cont_asie",
      "cont_amerique",
      "milieu_foret",
      "milieu_montagne",
      "classe_mammifere",
      "regime_carnivore",
      "taille_10k+",
      "lettre_l",
      "carac_groupe",
      "carac_solitaire"
    ]
  },
  {
    "name": "Lynx",
    "attrs": [
      "cont_europe",
      "cont_asie",
      "milieu_foret",
      "classe_mammifere",
      "regime_carnivore",
      "taille_10k+",
      "lettre_l",
      "carac_menace",
      "carac_solitaire",
      "carac_nocturne"
    ]
  },
  {
    "name": "Ours brun",
    "attrs": [
      "cont_europe",
      "cont_asie",
      "milieu_foret",
      "milieu_montagne",
      "classe_mammifere",
      "regime_omnivore",
      "taille_100k+",
      "lettre_o",
      "carac_solitaire"
    ]
  },
  {
    "name": "Renard roux",
    "attrs": [
      "cont_europe",
      "cont_asie",
      "milieu_foret",
      "classe_mammifere",
      "regime_omnivore",
      "taille_10k+",
      "lettre_r",
      "carac_nocturne",
      "carac_solitaire"
    ]
  },
  {
    "name": "Cerf",
    "attrs": [
      "cont_europe",
      "cont_asie",
      "milieu_foret",
      "classe_mammifere",
      "regime_herbivore",
      "taille_100k+",
      "lettre_c",
      "carac_groupe"
    ]
  },
  {
    "name": "Sanglier",
    "attrs": [
      "cont_europe",
      "cont_asie",
      "milieu_foret",
      "classe_mammifere",
      "regime_omnivore",
      "taille_100k+",
      "lettre_s",
      "carac_groupe",
      "carac_nocturne"
    ]
  },
  {
    "name": "Hérisson",
    "attrs": [
      "cont_europe",
      "milieu_foret",
      "classe_mammifere",
      "regime_omnivore",
      "taille_1k+",
      "syl_on",
      "lettre_h",
      "carac_nocturne",
      "carac_solitaire"
    ]
  },
  {
    "name": "Blaireau",
    "attrs": [
      "cont_europe",
      "milieu_foret",
      "classe_mammifere",
      "regime_omnivore",
      "taille_10k+",
      "syl_eau",
      "lettre_b",
      "carac_nocturne",
      "carac_groupe"
    ]
  },
  {
    "name": "Aigle royal",
    "attrs": [
      "cont_europe",
      "cont_asie",
      "cont_amerique",
      "milieu_montagne",
      "classe_oiseau",
      "regime_carnivore",
      "taille_10k+",
      "lettre_a",
      "carac_ovipare",
      "carac_solitaire"
    ]
  },
  {
    "name": "Cigogne",
    "attrs": [
      "cont_europe",
      "cont_afrique",
      "milieu_savane",
      "milieu_eau",
      "classe_oiseau",
      "regime_carnivore",
      "taille_10k+",
      "syl_ogne",
      "lettre_c",
      "carac_ovipare",
      "carac_migrateur"
    ]
  },
  {
    "name": "Hibou",
    "attrs": [
      "cont_europe",
      "cont_asie",
      "cont_amerique",
      "milieu_foret",
      "classe_oiseau",
      "regime_carnivore",
      "taille_1k+",
      "syl_ou",
      "lettre_h",
      "carac_nocturne",
      "carac_ovipare",
      "carac_solitaire"
    ]
  },
  {
    "name": "Chauve-souris",
    "attrs": [
      "cont_europe",
      "cont_asie",
      "cont_amerique",
      "cont_afrique",
      "milieu_foret",
      "classe_mammifere",
      "regime_carnivore",
      "taille_1k+",
      "lettre_c",
      "carac_nocturne",
      "carac_volant"
    ]
  },
  {
    "name": "Vipère",
    "attrs": [
      "cont_europe",
      "cont_asie",
      "milieu_foret",
      "classe_reptile",
      "regime_carnivore",
      "taille_1k+",
      "syl_ere",
      "lettre_v",
      "carac_venimeux",
      "carac_ovipare",
      "carac_solitaire"
    ]
  },
  {
    "name": "Chouette",
    "attrs": [
      "cont_europe",
      "cont_asie",
      "cont_amerique",
      "milieu_foret",
      "classe_oiseau",
      "regime_carnivore",
      "taille_1k+",
      "syl_ette",
      "lettre_c",
      "carac_nocturne",
      "carac_ovipare",
      "carac_solitaire"
    ]
  },
  {
    "name": "Chevrette",
    "attrs": [
      "cont_europe",
      "milieu_foret",
      "milieu_montagne",
      "classe_mammifere",
      "regime_herbivore",
      "taille_10k+",
      "syl_ette",
      "lettre_c",
      "carac_groupe"
    ]
  },
  {
    "name": "Marmotte",
    "attrs": [
      "cont_europe",
      "cont_asie",
      "cont_amerique",
      "milieu_montagne",
      "classe_mammifere",
      "regime_herbivore",
      "taille_1k+",
      "syl_otte",
      "lettre_m",
      "carac_groupe"
    ]
  },
  {
    "name": "Castor",
    "attrs": [
      "cont_europe",
      "cont_amerique",
      "milieu_eau",
      "classe_mammifere",
      "regime_herbivore",
      "taille_10k+",
      "syl_or",
      "lettre_c",
      "carac_groupe",
      "carac_nageur"
    ]
  },
  {
    "name": "Loutre",
    "attrs": [
      "cont_europe",
      "cont_asie",
      "cont_amerique",
      "milieu_eau",
      "classe_mammifere",
      "regime_carnivore",
      "taille_10k+",
      "lettre_l",
      "carac_nageur",
      "carac_menace"
    ]
  },
  {
    "name": "Dauphin",
    "attrs": [
      "cont_europe",
      "cont_afrique",
      "cont_amerique",
      "milieu_mer",
      "classe_mammifere",
      "regime_carnivore",
      "taille_100k+",
      "syl_in",
      "lettre_d",
      "carac_groupe",
      "carac_nageur"
    ]
  },
  {
    "name": "Baleine bleue",
    "attrs": [
      "cont_arctique",
      "cont_antarctique",
      "milieu_mer",
      "classe_mammifere",
      "regime_carnivore",
      "taille_1000k+",
      "lettre_b",
      "carac_menace",
      "carac_nageur",
      "carac_migrateur"
    ]
  },
  {
    "name": "Grand requin blanc",
    "attrs": [
      "cont_afrique",
      "cont_amerique",
      "cont_oceanie",
      "milieu_mer",
      "classe_poisson",
      "regime_carnivore",
      "taille_1000k+",
      "lettre_g",
      "carac_solitaire",
      "carac_nageur",
      "carac_menace"
    ]
  },
  {
    "name": "Raie manta",
    "attrs": [
      "cont_afrique",
      "cont_asie",
      "cont_amerique",
      "milieu_mer",
      "classe_poisson",
      "regime_carnivore",
      "taille_100k+",
      "lettre_r",
      "carac_nageur",
      "carac_migrateur",
      "carac_menace"
    ]
  },
  {
    "name": "Méduse",
    "attrs": [
      "cont_europe",
      "cont_afrique",
      "cont_asie",
      "milieu_mer",
      "classe_autre",
      "regime_carnivore",
      "taille_1k+",
      "lettre_m",
      "carac_venimeux",
      "carac_nageur"
    ]
  },
  {
    "name": "Pieuvre",
    "attrs": [
      "cont_europe",
      "cont_afrique",
      "cont_asie",
      "milieu_mer",
      "classe_autre",
      "regime_carnivore",
      "taille_10k+",
      "lettre_p",
      "carac_nageur",
      "carac_solitaire"
    ]
  },
  {
    "name": "Hippocampe",
    "attrs": [
      "cont_europe",
      "cont_afrique",
      "cont_asie",
      "milieu_mer",
      "classe_poisson",
      "regime_carnivore",
      "taille_1k+",
      "syl_ampe",
      "lettre_h",
      "carac_nageur",
      "carac_menace"
    ]
  },
  {
    "name": "Tortue marine",
    "attrs": [
      "cont_afrique",
      "cont_asie",
      "cont_amerique",
      "milieu_mer",
      "classe_reptile",
      "regime_herbivore",
      "taille_100k+",
      "lettre_t",
      "carac_ovipare",
      "carac_nageur",
      "carac_menace",
      "carac_migrateur"
    ]
  },
  {
    "name": "Clown (poisson)",
    "attrs": [
      "cont_asie",
      "cont_oceanie",
      "milieu_mer",
      "classe_poisson",
      "regime_omnivore",
      "taille_1k+",
      "syl_on",
      "lettre_c",
      "carac_nageur"
    ]
  },
  {
    "name": "Phoque",
    "attrs": [
      "cont_arctique",
      "cont_europe",
      "milieu_mer",
      "classe_mammifere",
      "regime_carnivore",
      "taille_100k+",
      "lettre_p",
      "carac_nageur",
      "carac_groupe"
    ]
  },
  {
    "name": "Calamar géant",
    "attrs": [
      "cont_arctique",
      "cont_antarctique",
      "milieu_mer",
      "classe_autre",
      "regime_carnivore",
      "taille_100k+",
      "lettre_c",
      "carac_nageur",
      "carac_solitaire"
    ]
  },
  {
    "name": "Cheval",
    "attrs": [
      "cont_europe",
      "cont_asie",
      "cont_amerique",
      "milieu_savane",
      "classe_mammifere",
      "regime_herbivore",
      "taille_100k+",
      "lettre_c",
      "carac_groupe",
      "carac_domestique"
    ]
  },
  {
    "name": "Vache",
    "attrs": [
      "cont_europe",
      "milieu_savane",
      "classe_mammifere",
      "regime_herbivore",
      "taille_100k+",
      "lettre_v",
      "carac_groupe",
      "carac_domestique"
    ]
  },
  {
    "name": "Mouton",
    "attrs": [
      "cont_europe",
      "cont_oceanie",
      "milieu_montagne",
      "milieu_savane",
      "classe_mammifere",
      "regime_herbivore",
      "taille_10k+",
      "syl_on",
      "lettre_m",
      "carac_groupe",
      "carac_domestique"
    ]
  },
  {
    "name": "Chèvre",
    "attrs": [
      "cont_europe",
      "cont_asie",
      "milieu_montagne",
      "classe_mammifere",
      "regime_herbivore",
      "taille_10k+",
      "syl_evre",
      "lettre_c",
      "carac_groupe",
      "carac_domestique"
    ]
  },
  {
    "name": "Cochon",
    "attrs": [
      "cont_europe",
      "cont_asie",
      "milieu_foret",
      "classe_mammifere",
      "regime_omnivore",
      "taille_100k+",
      "syl_on",
      "lettre_c",
      "carac_groupe",
      "carac_domestique"
    ]
  },
  {
    "name": "Chat",
    "attrs": [
      "cont_europe",
      "cont_asie",
      "milieu_foret",
      "classe_mammifere",
      "regime_carnivore",
      "taille_1k+",
      "lettre_c",
      "carac_nocturne",
      "carac_solitaire",
      "carac_domestique"
    ]
  },
  {
    "name": "Chien",
    "attrs": [
      "cont_europe",
      "cont_asie",
      "cont_amerique",
      "milieu_foret",
      "milieu_savane",
      "classe_mammifere",
      "regime_omnivore",
      "taille_10k+",
      "syl_ien",
      "lettre_c",
      "carac_groupe",
      "carac_domestique"
    ]
  },
  {
    "name": "Lapin",
    "attrs": [
      "cont_europe",
      "milieu_foret",
      "classe_mammifere",
      "regime_herbivore",
      "taille_1k+",
      "syl_in",
      "lettre_l",
      "carac_groupe",
      "carac_domestique",
      "carac_ovipare"
    ]
  },
  {
    "name": "Perroquet",
    "attrs": [
      "cont_amerique",
      "cont_asie",
      "cont_oceanie",
      "milieu_foret",
      "classe_oiseau",
      "regime_omnivore",
      "taille_1k+",
      "syl_et",
      "lettre_p",
      "carac_ovipare",
      "carac_arboricole",
      "carac_domestique"
    ]
  },
  {
    "name": "Poule",
    "attrs": [
      "cont_europe",
      "cont_asie",
      "milieu_savane",
      "classe_oiseau",
      "regime_omnivore",
      "taille_1k+",
      "lettre_p",
      "carac_ovipare",
      "carac_groupe",
      "carac_domestique"
    ]
  },
  {
    "name": "Canard",
    "attrs": [
      "cont_europe",
      "cont_asie",
      "cont_amerique",
      "milieu_eau",
      "classe_oiseau",
      "regime_omnivore",
      "taille_1k+",
      "syl_ard",
      "lettre_c",
      "carac_ovipare",
      "carac_nageur",
      "carac_domestique",
      "carac_migrateur"
    ]
  },
  {
    "name": "Abeille",
    "attrs": [
      "cont_europe",
      "cont_afrique",
      "cont_asie",
      "milieu_foret",
      "classe_insecte",
      "regime_herbivore",
      "taille_1k+",
      "syl_eille",
      "lettre_a",
      "carac_venimeux",
      "carac_groupe",
      "carac_volant",
      "carac_domestique"
    ]
  },
  {
    "name": "Ver de terre",
    "attrs": [
      "cont_europe",
      "cont_asie",
      "cont_amerique",
      "milieu_foret",
      "classe_autre",
      "regime_omnivore",
      "taille_1k+",
      "lettre_v",
      "carac_solitaire"
    ]
  },
  {
    "name": "Fourmi",
    "attrs": [
      "cont_europe",
      "cont_afrique",
      "cont_asie",
      "cont_amerique",
      "milieu_foret",
      "classe_insecte",
      "regime_omnivore",
      "taille_1k+",
      "lettre_f",
      "carac_groupe",
      "carac_volant"
    ]
  },
  {
    "name": "Papillon",
    "attrs": [
      "cont_europe",
      "cont_afrique",
      "cont_asie",
      "cont_amerique",
      "milieu_foret",
      "classe_insecte",
      "regime_herbivore",
      "taille_1k+",
      "syl_on",
      "lettre_p",
      "carac_volant",
      "carac_migrateur"
    ]
  },
  {
    "name": "Libellule",
    "attrs": [
      "cont_europe",
      "cont_asie",
      "cont_amerique",
      "milieu_eau",
      "classe_insecte",
      "regime_carnivore",
      "taille_1k+",
      "syl_ule",
      "lettre_l",
      "carac_volant"
    ]
  },
  {
    "name": "Moustique",
    "attrs": [
      "cont_europe",
      "cont_afrique",
      "cont_asie",
      "cont_amerique",
      "milieu_eau",
      "classe_insecte",
      "regime_carnivore",
      "taille_1k+",
      "lettre_m",
      "carac_volant",
      "carac_venimeux"
    ]
  },
  {
    "name": "Scarabée",
    "attrs": [
      "cont_europe",
      "cont_afrique",
      "cont_asie",
      "milieu_foret",
      "milieu_savane",
      "classe_insecte",
      "regime_omnivore",
      "taille_1k+",
      "lettre_s",
      "carac_nocturne"
    ]
  },
  {
    "name": "Sauterelle",
    "attrs": [
      "cont_europe",
      "cont_afrique",
      "cont_asie",
      "milieu_savane",
      "classe_insecte",
      "regime_herbivore",
      "taille_1k+",
      "syl_elle",
      "lettre_s",
      "carac_groupe",
      "carac_volant"
    ]
  },
  {
    "name": "Araignée",
    "attrs": [
      "cont_europe",
      "cont_afrique",
      "cont_asie",
      "cont_amerique",
      "milieu_foret",
      "classe_autre",
      "regime_carnivore",
      "taille_1k+",
      "lettre_a",
      "carac_venimeux",
      "carac_solitaire"
    ]
  },
  {
    "name": "Scorpion",
    "attrs": [
      "cont_afrique",
      "cont_asie",
      "cont_amerique",
      "milieu_desert",
      "classe_autre",
      "regime_carnivore",
      "taille_1k+",
      "syl_on",
      "lettre_s",
      "carac_venimeux",
      "carac_nocturne",
      "carac_solitaire"
    ]
  },
  {
    "name": "Caméléon",
    "attrs": [
      "cont_afrique",
      "milieu_foret",
      "classe_reptile",
      "regime_carnivore",
      "taille_1k+",
      "syl_on",
      "lettre_c",
      "carac_ovipare",
      "carac_arboricole",
      "carac_solitaire"
    ]
  },
  {
    "name": "Gecko",
    "attrs": [
      "cont_afrique",
      "cont_asie",
      "cont_oceanie",
      "milieu_foret",
      "milieu_desert",
      "classe_reptile",
      "regime_carnivore",
      "taille_1k+",
      "lettre_g",
      "carac_nocturne",
      "carac_ovipare"
    ]
  },
  {
    "name": "Iguane",
    "attrs": [
      "cont_amerique",
      "milieu_foret",
      "classe_reptile",
      "regime_herbivore",
      "taille_10k+",
      "syl_ane",
      "lettre_i",
      "carac_ovipare",
      "carac_arboricole"
    ]
  },
  {
    "name": "Tortue des Galápagos",
    "attrs": [
      "cont_amerique",
      "milieu_savane",
      "classe_reptile",
      "regime_herbivore",
      "taille_100k+",
      "lettre_t",
      "carac_ovipare",
      "carac_menace",
      "carac_solitaire"
    ]
  },
  {
    "name": "Axolotl",
    "attrs": [
      "cont_amerique",
      "milieu_eau",
      "classe_amphibien",
      "regime_carnivore",
      "taille_1k+",
      "lettre_a",
      "carac_menace"
    ]
  },
  {
    "name": "Grenouille",
    "attrs": [
      "cont_europe",
      "cont_asie",
      "cont_amerique",
      "cont_afrique",
      "milieu_eau",
      "classe_amphibien",
      "regime_carnivore",
      "taille_1k+",
      "syl_ille",
      "lettre_g",
      "carac_ovipare",
      "carac_nageur"
    ]
  },
  {
    "name": "Salamandre",
    "attrs": [
      "cont_europe",
      "cont_asie",
      "cont_amerique",
      "milieu_foret",
      "milieu_eau",
      "classe_amphibien",
      "regime_carnivore",
      "taille_1k+",
      "syl_andre",
      "lettre_s",
      "carac_nocturne",
      "carac_venimeux"
    ]
  },
  {
    "name": "Crapaud",
    "attrs": [
      "cont_europe",
      "cont_afrique",
      "cont_amerique",
      "milieu_foret",
      "milieu_eau",
      "classe_amphibien",
      "regime_carnivore",
      "taille_1k+",
      "syl_aud",
      "lettre_c",
      "carac_nocturne",
      "carac_ovipare"
    ]
  },
  {
    "name": "Triton",
    "attrs": [
      "cont_europe",
      "milieu_eau",
      "classe_amphibien",
      "regime_carnivore",
      "taille_1k+",
      "syl_on",
      "lettre_t",
      "carac_nageur",
      "carac_ovipare"
    ]
  },
  {
    "name": "Suricate",
    "attrs": [
      "cont_afrique",
      "milieu_desert",
      "milieu_savane",
      "classe_mammifere",
      "regime_omnivore",
      "taille_1k+",
      "syl_ate",
      "lettre_s",
      "carac_groupe"
    ]
  },
  {
    "name": "Fennec",
    "attrs": [
      "cont_afrique",
      "milieu_desert",
      "classe_mammifere",
      "regime_omnivore",
      "taille_1k+",
      "lettre_f",
      "carac_nocturne",
      "carac_solitaire"
    ]
  },
  {
    "name": "Dromadaire",
    "attrs": [
      "cont_afrique",
      "cont_asie",
      "milieu_desert",
      "classe_mammifere",
      "regime_herbivore",
      "taille_100k+",
      "syl_aire",
      "lettre_d",
      "carac_groupe",
      "carac_domestique"
    ]
  },
  {
    "name": "Chameau",
    "attrs": [
      "cont_asie",
      "milieu_desert",
      "classe_mammifere",
      "regime_herbivore",
      "taille_100k+",
      "syl_eau",
      "lettre_c",
      "carac_groupe",
      "carac_domestique"
    ]
  },
  {
    "name": "Gazelle",
    "attrs": [
      "cont_afrique",
      "cont_asie",
      "milieu_savane",
      "milieu_desert",
      "classe_mammifere",
      "regime_herbivore",
      "taille_10k+",
      "syl_elle",
      "lettre_g",
      "carac_groupe",
      "carac_menace"
    ]
  },
  {
    "name": "Gnou",
    "attrs": [
      "cont_afrique",
      "milieu_savane",
      "classe_mammifere",
      "regime_herbivore",
      "taille_100k+",
      "syl_ou",
      "lettre_g",
      "carac_groupe",
      "carac_migrateur"
    ]
  },
  {
    "name": "Phacochère",
    "attrs": [
      "cont_afrique",
      "milieu_savane",
      "classe_mammifere",
      "regime_omnivore",
      "taille_100k+",
      "lettre_p",
      "carac_groupe"
    ]
  },
  {
    "name": "Vautour",
    "attrs": [
      "cont_afrique",
      "cont_europe",
      "cont_asie",
      "milieu_montagne",
      "milieu_savane",
      "classe_oiseau",
      "regime_carnivore",
      "taille_10k+",
      "syl_our",
      "lettre_v",
      "carac_ovipare",
      "carac_volant",
      "carac_groupe"
    ]
  },
  {
    "name": "Pélican",
    "attrs": [
      "cont_afrique",
      "cont_europe",
      "cont_asie",
      "milieu_eau",
      "classe_oiseau",
      "regime_carnivore",
      "taille_10k+",
      "syl_an",
      "lettre_p",
      "carac_ovipare",
      "carac_nageur",
      "carac_migrateur",
      "carac_groupe"
    ]
  },
  {
    "name": "Macareux",
    "attrs": [
      "cont_arctique",
      "cont_europe",
      "milieu_mer",
      "classe_oiseau",
      "regime_carnivore",
      "taille_1k+",
      "lettre_m",
      "carac_ovipare",
      "carac_nageur",
      "carac_groupe"
    ]
  },
  {
    "name": "Harfang des neiges",
    "attrs": [
      "cont_arctique",
      "milieu_montagne",
      "classe_oiseau",
      "regime_carnivore",
      "taille_10k+",
      "lettre_h",
      "carac_ovipare",
      "carac_solitaire",
      "carac_nocturne"
    ]
  },
  {
    "name": "Renne",
    "attrs": [
      "cont_arctique",
      "cont_europe",
      "milieu_montagne",
      "classe_mammifere",
      "regime_herbivore",
      "taille_100k+",
      "lettre_r",
      "carac_groupe",
      "carac_migrateur",
      "carac_domestique"
    ]
  },
  {
    "name": "Élan",
    "attrs": [
      "cont_arctique",
      "cont_europe",
      "cont_amerique",
      "milieu_foret",
      "milieu_eau",
      "classe_mammifere",
      "regime_herbivore",
      "taille_100k+",
      "syl_an",
      "lettre_e",
      "carac_solitaire",
      "carac_nageur"
    ]
  }
]